[
  {
    "id": 2116090,
    "reg": "VT-TVD",
    "active": true,
    "serial": "10377",
    "hexIcao": "801464",
    "airlineName": "Air India",
    "iataCodeShort": "32Q",
    "icaoCode": "A21N",
    "model": "A21N",
    "modelCode": "321-251NX",
    "numSeats": 188,
    "rolloutDate": "2021-09-02",
    "firstFlightDate": "2021-09-02",
    "deliveryDate": "2021-10-06",
    "registrationDate": "2024-11-11",
    "typeName": "Airbus A321 NEO",
    "numEngines": 2,
    "engineType": "Jet",
    "isFreighter": false,
    "productionLine": "Airbus A321 NEO",
    "ageYears": 4.3,
    "verified": true,
    "numRegistrations": 2
  },
  {
    "id": 2116090,
    "reg": "VT-TVD",
    "active": true,
    "serial": "10377",
    "hexIcao": "801464",
    "airlineName": "Air India",
    "iataCodeShort": "32Q",
    "icaoCode": "A21N",
    "model": "A21N",
    "modelCode": "321-251NX",
    "numSeats": 188,
    "rolloutDate": "2021-09-02",
    "firstFlightDate": "2021-09-02",
    "deliveryDate": "2021-10-06",
    "registrationDate": "2024-11-11",
    "typeName": "Airbus A321 NEO",
    "numEngines": 2,
    "engineType": "Jet",
    "isFreighter": false,
    "productionLine": "Airbus A321 NEO",
    "ageYears": 4.3,
    "verified": true,
    "numRegistrations": 2
  }
]